sparkorm/__init__.py
sparkorm/accessors.py
sparkorm/base_field.py
sparkorm/exceptions.py
sparkorm/fields.py
sparkorm/formatters.py
sparkorm/metadata_types.py
sparkorm/models.py
sparkorm/py.typed
sparkorm/schema_builder.py
sparkorm/schema_merger.py
sparkorm/struct.py
sparkorm/utils.py
sparkorm-1.2.29.dist-info/entry_points.txt
sparkorm-1.2.29.dist-info/LICENSE
sparkorm-1.2.29.dist-info/METADATA
sparkorm-1.2.29.dist-info/WHEEL
sparkorm-1.2.29.dist-info/RECORD
