Metadata-Version: 2.1
Name: sparkorm
Version: 1.2.29
Summary: SparkORM: Python Spark SQL & DataFrame schema management and basic Object Relational Mapping.
Home-page: https://github.com/asuiu/sparkorm
License: MIT
Author: Andrei Suiu
Author-email: andrei.suiu@gmail.com
Requires-Python: >=3.8,<4.0.0
Classifier: License :: OSI Approved :: MIT License
Classifier: Programming Language :: Python :: 3
Classifier: Programming Language :: Python :: 3.8
Classifier: Programming Language :: Python :: 3.9
Classifier: Programming Language :: Python :: 3.10
Classifier: Programming Language :: Python :: 3.11
Classifier: Programming Language :: Python :: 3.12
Provides-Extra: pyspark
Requires-Dist: StrEnum (>=0.4.0)
Requires-Dist: streamerate (>=1,<2)
Requires-Dist: tsx (>=0.1.16)
Project-URL: Repository, https://github.com/asuiu/sparkorm
